forayer/__init__.py
forayer/datasets/__init__.py
forayer/datasets/base_dataset.py
forayer/datasets/oaei_kg.py
forayer/datasets/open_ea.py
forayer/evaluation/__init__.py
forayer/evaluation/er_metrics.py
forayer/exploration/attributes.py
forayer/input_output/__init__.py
forayer/input_output/from_to_gradoop.py
forayer/input_output/from_to_open_ea.py
forayer/input_output/from_to_rdf.py
forayer/knowledge_graph/__init__.py
forayer/knowledge_graph/clusters.py
forayer/knowledge_graph/er_task.py
forayer/knowledge_graph/graph_based_clustering.py
forayer/knowledge_graph/kg.py
forayer/transformation/__init__.py
forayer/transformation/word_embedding.py
forayer/utils/dict_help.py
forayer/utils/random_help.py
forayer-0.4.4.dist-info/LICENSE
forayer-0.4.4.dist-info/WHEEL
forayer-0.4.4.dist-info/METADATA
forayer-0.4.4.dist-info/RECORD
