Metadata-Version: 2.1
Name: forayer
Version: 0.4.4
Summary: First aid utilies for knowledge graph exploration with an entity centric approach
Home-page: https://github.com/dobraczka/forayer
License: MIT
Keywords: knowledge graph,entity resolution
Author: Daniel Obraczka
Author-email: obraczka@informatik.uni-leipzig.de
Requires-Python: >=3.8,<4.0
Classifier: Development Status :: 4 - Beta
Classifier: License :: OSI Approved :: MIT License
Classifier: Programming Language :: Python
Classifier: Programming Language :: Python :: 3
Classifier: Programming Language :: Python :: 3.8
Classifier: Programming Language :: Python :: 3.9
Classifier: Programming Language :: Python :: 3.10
Classifier: Programming Language :: Python :: 3.11
Classifier: Programming Language :: Python :: 3 :: Only
Classifier: Programming Language :: Python :: 3.10
Classifier: Programming Language :: Python :: 3.11
Classifier: Programming Language :: Python :: 3.8
Classifier: Programming Language :: Python :: 3.9
Provides-Extra: docs
Requires-Dist: gensim (>=4.2.0,<5.0.0)
Requires-Dist: insegel (>=1.1.0,<2.0.0) ; extra == "docs"
Requires-Dist: joblib (>=1.2.0,<2.0.0)
Requires-Dist: networkx (>=2.6.2,<3.0.0)
Requires-Dist: numpy (>=1.22,<2.0)
Requires-Dist: numpydoc (>=1.1.0,<2.0.0)
Requires-Dist: pandas (>=1.3.2,<2.0.0)
Requires-Dist: plotly (>=5.2.1,<6.0.0)
Requires-Dist: pystow (>=0.3,<0.4)
Requires-Dist: rdflib (>=6.0.0,<7.0.0)
Requires-Dist: scikit-learn (>=1.0.1,<2.0.0)
Requires-Dist: sphinx (>=4.0.2,<5.0.0) ; extra == "docs"
Requires-Dist: tqdm (>=4.0,<5.0)
Requires-Dist: wget (>=3.2,<4.0)
Project-URL: Bug Tracker, https://github.com/dobraczka/forayer/issues
Project-URL: Documentation, https://forayer.readthedocs.io
Project-URL: Repository, https://github.com/dobraczka/forayer
Project-URL: Source, https://github.com/dobraczka/forayer
